aioairzone_cloud/__init__.py
aioairzone_cloud/aidoo.py
aioairzone_cloud/air_quality.py
aioairzone_cloud/cloudapi.py
aioairzone_cloud/common.py
aioairzone_cloud/const.py
aioairzone_cloud/device.py
aioairzone_cloud/device_group.py
aioairzone_cloud/entity.py
aioairzone_cloud/exceptions.py
aioairzone_cloud/group.py
aioairzone_cloud/hotwater.py
aioairzone_cloud/hvac.py
aioairzone_cloud/installation.py
aioairzone_cloud/output.py
aioairzone_cloud/py.typed
aioairzone_cloud/system.py
aioairzone_cloud/token.py
aioairzone_cloud/webserver.py
aioairzone_cloud/websockets.py
aioairzone_cloud/zone.py
aioairzone_cloud-0.7.2.dist-info/licenses/LICENSE
aioairzone_cloud-0.7.2.dist-info/METADATA
aioairzone_cloud-0.7.2.dist-info/WHEEL
aioairzone_cloud-0.7.2.dist-info/top_level.txt
aioairzone_cloud-0.7.2.dist-info/RECORD
